buddybet_logmon_common/__init__.py
buddybet_logmon_common/fastapi_logger.py
buddybet_logmon_common/logger.py
buddybet_logmon_common-0.1.0.dist-info/METADATA
buddybet_logmon_common-0.1.0.dist-info/WHEEL
buddybet_logmon_common-0.1.0.dist-info/RECORD
