Metadata-Version: 2.3
Name: buddybet-logmon-common
Version: 0.1.0
Summary: Librería de logging en formato JSON con integración para FastAPI
License: MIT
Keywords: logging,json,fastapi,monitoring,observability
Author: ricardomarzochi07
Author-email: ricardomarzochi@gmail.com
Requires-Python: >=3.12
Classifier: License :: OSI Approved :: MIT License
Classifier: Programming Language :: Python :: 3
Classifier: Programming Language :: Python :: 3.12
Classifier: Programming Language :: Python :: 3.13
Requires-Dist: fastapi (>=0.116.1,<0.117.0)
